pyetheroll/__init__.py
pyetheroll/constants.py
pyetheroll/etheroll.py
pyetheroll/etherscan_utils.py
pyetheroll/transaction_debugger.py
pyetheroll/utils.py
etheroll-20200322.dist-info/LICENSE
etheroll-20200322.dist-info/METADATA
etheroll-20200322.dist-info/WHEEL
etheroll-20200322.dist-info/dependency_links.txt
etheroll-20200322.dist-info/top_level.txt
etheroll-20200322.dist-info/RECORD
