Metadata-Version: 2.1
Name: etheroll
Version: 20200322
Summary: Python library to Etheroll smart contract
Home-page: https://github.com/AndreMiras/pyetheroll
Author: Andre Miras
License: UNKNOWN
Platform: UNKNOWN
Requires-Dist: pyetheroll
